text2tree
