Metadata-Version: 1.0
Name: text2tree
Version: 0.5
Summary: Description text
Home-page: https://github.com/tklijnsma/text2tree.git
Author: Thomas Klijnsma
Author-email: tklijnsm@gmail.com
License: BSD 3-Clause License
Platform: UNKNOWN
